{"version":3,"kind":"Article","sha256":"67475fe69b86b0a8360bd6a0b02fd2b11b13b491371fe67fc19f0129f6e73033","slug":"events.uc-open-4-2025.sessions.how-can-we-help","location":"/events/uc-open-4-2025/sessions/how-can-we-help.md","dependencies":[],"frontmatter":{"title":"Directed Discussion: How can we help? - Academic OSPOs Making an Impact at UC","github":"https://github.com/UC-OSPO-Network/ucospo.net","copyright":"2024","numbering":{"title":{"offset":1}},"source_url":"https://github.com/UC-OSPO-Network/ucospo.net/blob/main/events/uc-open-4-2025/sessions/how-can-we-help.md","edit_url":"https://github.com/UC-OSPO-Network/ucospo.net/edit/main/events/uc-open-4-2025/sessions/how-can-we-help.md","exports":[{"format":"md","filename":"how-can-we-help.md","url":"/build/how-can-we-help-25c543267dc4d4fc2388ebad69b0c537.md"}]},"mdast":{"type":"root","children":[{"type":"block","children":[{"type":"paragraph","position":{"start":{"line":5,"column":1},"end":{"line":6,"column":1}},"children":[{"type":"strong","position":{"start":{"line":5,"column":1},"end":{"line":5,"column":1}},"children":[{"type":"text","value":"Date:","position":{"start":{"line":5,"column":1},"end":{"line":5,"column":1}},"key":"AV5CyYGTt8"}],"key":"ITswEZYhDT"},{"type":"text","value":" Thursday, April 24 2025","position":{"start":{"line":5,"column":1},"end":{"line":5,"column":1}},"key":"Tp3yEDbZkF"},{"type":"break","position":{"start":{"line":5,"column":1},"end":{"line":5,"column":1}},"key":"xnLNUC4dEN"},{"type":"strong","position":{"start":{"line":5,"column":1},"end":{"line":5,"column":1}},"children":[{"type":"text","value":"Time:","position":{"start":{"line":5,"column":1},"end":{"line":5,"column":1}},"key":"vHWea4yCCW"}],"key":"beVIFHlhSZ"},{"type":"text","value":" 3:00-3:50","position":{"start":{"line":5,"column":1},"end":{"line":5,"column":1}},"key":"kEOldjbQBP"}],"key":"TDjA0vECWO"},{"type":"paragraph","position":{"start":{"line":8,"column":1},"end":{"line":8,"column":1}},"children":[{"type":"strong","position":{"start":{"line":8,"column":1},"end":{"line":8,"column":1}},"children":[{"type":"text","value":"Moderator","position":{"start":{"line":8,"column":1},"end":{"line":8,"column":1}},"key":"pZD7fEL4kM"}],"key":"ZYqIY6fCr2"},{"type":"text","value":": ","position":{"start":{"line":8,"column":1},"end":{"line":8,"column":1}},"key":"T3zRJ8WBMd"},{"type":"link","url":"/events/uc-open-4-2025/speakers/laura-langdon","position":{"start":{"line":8,"column":1},"end":{"line":8,"column":1}},"children":[{"type":"text","value":"Laura Langdon (Community Manager, UC OSPO Network)","position":{"start":{"line":8,"column":1},"end":{"line":8,"column":1}},"key":"PmeYYS5Asm"}],"urlSource":"../speakers/laura-langdon.md","dataUrl":"/events.uc-open-4-2025.speakers.laura-langdon.json","internal":true,"protocol":"file","key":"XSU8LnwdJI"}],"key":"gRG2TOuGub"},{"type":"heading","depth":2,"position":{"start":{"line":10,"column":1},"end":{"line":10,"column":1}},"children":[{"type":"text","value":"Description","position":{"start":{"line":10,"column":1},"end":{"line":10,"column":1}},"key":"UNwE7u3a1g"}],"identifier":"description","label":"Description","html_id":"description","implicit":true,"key":"BShUJTddGD"},{"type":"paragraph","position":{"start":{"line":12,"column":1},"end":{"line":12,"column":1}},"children":[{"type":"text","value":"How can the OSPO Network support your open source work? We can’t wait to hear from you!","position":{"start":{"line":12,"column":1},"end":{"line":12,"column":1}},"key":"zYnZXOR9Ma"}],"key":"uI40LVO0k2"}],"key":"vw8D8F5Srx"}],"key":"aBtLVQis4r"},"references":{"cite":{"order":[],"data":{}}},"footer":{},"domain":"http://localhost:3000"}