{"version":3,"kind":"Article","sha256":"fb401a13862d6af78258d3275b6b9a4a00f73fc2ed9e894347d057caadeac6d3","slug":"events.uc-open-4-2025.speakers.colleen-josephson","location":"/events/uc-open-4-2025/speakers/colleen-josephson.md","dependencies":[],"frontmatter":{"title":"Colleen Josephson","github":"https://github.com/UC-OSPO-Network/ucospo.net","copyright":"2024","numbering":{"title":{"offset":1}},"source_url":"https://github.com/UC-OSPO-Network/ucospo.net/blob/main/events/uc-open-4-2025/speakers/colleen-josephson.md","edit_url":"https://github.com/UC-OSPO-Network/ucospo.net/edit/main/events/uc-open-4-2025/speakers/colleen-josephson.md","thumbnail":"/build/colleen-josephson-1d6e812e616a1a38c80fd61f5597af34.png","exports":[{"format":"md","filename":"colleen-josephson.md","url":"/build/colleen-josephson-59b10efe31ec2016e52ed0f448f0ed77.md"}]},"mdast":{"type":"root","children":[{"type":"block","children":[{"type":"image","url":"/build/colleen-josephson-1d6e812e616a1a38c80fd61f5597af34.png","alt":"Speaker photo","position":{"start":{"line":5,"column":1},"end":{"line":5,"column":1}},"key":"RUe1lKVYgY","urlSource":"headshots/colleen-josephson.png"},{"type":"paragraph","position":{"start":{"line":7,"column":1},"end":{"line":7,"column":1}},"children":[{"type":"link","url":"https://www.linkedin.com/in/colleen-josephson-4b3a9216/","position":{"start":{"line":7,"column":1},"end":{"line":7,"column":1}},"children":[{"type":"text","value":"Colleen’s","position":{"start":{"line":7,"column":1},"end":{"line":7,"column":1}},"key":"eTIelxRDNY"}],"urlSource":"https://www.linkedin.com/in/colleen-josephson-4b3a9216/","key":"bRI1ajEZgP"},{"type":"text","value":" work includes designing novel sensing paradigms for agriculture, inventing techniques for ultra-low power communication in indoor sensor networks, and exploiting non-traditional energy sources, such as microbes, for sustainable sensing. The vast majority of the work her group conducts is released in the public domain via ","position":{"start":{"line":7,"column":1},"end":{"line":7,"column":1}},"key":"Efe2AFmgIZ"},{"type":"link","url":"https://github.com/jlab-sensing","position":{"start":{"line":7,"column":1},"end":{"line":7,"column":1}},"children":[{"type":"text","value":"open-source artifacts","position":{"start":{"line":7,"column":1},"end":{"line":7,"column":1}},"key":"SKSywoFS2q"}],"urlSource":"https://github.com/jlab-sensing","error":true,"key":"IcWTm8QMC8"},{"type":"text","value":". Colleen has also recently been named Co-Director of the ","position":{"start":{"line":7,"column":1},"end":{"line":7,"column":1}},"key":"bLZLCrl0OC"},{"type":"link","url":"https://agtech.ucsc.edu/","position":{"start":{"line":7,"column":1},"end":{"line":7,"column":1}},"children":[{"type":"text","value":"UCSC Agtech Alliance","position":{"start":{"line":7,"column":1},"end":{"line":7,"column":1}},"key":"Q6KT0ZqkYg"}],"urlSource":"https://agtech.ucsc.edu/","key":"e6kgaWSBVG"},{"type":"text","value":" to promote inter-disciplinary ethical solutions to tomorrow’s AgTech challenges.","position":{"start":{"line":7,"column":1},"end":{"line":7,"column":1}},"key":"uxUFoKK4qO"}],"key":"kqE06eaOme"},{"type":"heading","depth":2,"position":{"start":{"line":9,"column":1},"end":{"line":9,"column":1}},"children":[{"type":"text","value":"Session","position":{"start":{"line":9,"column":1},"end":{"line":9,"column":1}},"key":"d3HStxr6ln"}],"identifier":"session","label":"Session","html_id":"session","implicit":true,"key":"WMRjYkfzdm"},{"type":"paragraph","position":{"start":{"line":11,"column":1},"end":{"line":11,"column":1}},"children":[{"type":"link","url":"/events/uc-open-4-2025/sessions/agrifood","position":{"start":{"line":11,"column":1},"end":{"line":11,"column":1}},"children":[{"type":"text","value":"Open Source for Agrifood – Perspectives from Academia and Industry","position":{"start":{"line":11,"column":1},"end":{"line":11,"column":1}},"key":"VNSLIMzNg7"}],"urlSource":"../sessions/agrifood.md","dataUrl":"/events.uc-open-4-2025.sessions.agrifood.json","internal":true,"protocol":"file","key":"Gkda4f2IX4"}],"key":"ipXd2ZPssK"}],"key":"Pixjf0vLIc"}],"key":"zPWLOXriIc"},"references":{"cite":{"order":[],"data":{}}},"footer":{},"domain":"http://localhost:3000"}