{"version":3,"kind":"Article","sha256":"bf1fdf0644ef7672e27238390fb9492b096687b93fda4724fad87b6b4db7e7c3","slug":"events.uc-open-4-2025.sessions.oss-security-ai","location":"/events/uc-open-4-2025/sessions/oss-security-ai.md","dependencies":[],"frontmatter":{"title":"Technical Session: Open Source Software Security in AI","github":"https://github.com/UC-OSPO-Network/ucospo.net","copyright":"2024","numbering":{"title":{"offset":1}},"source_url":"https://github.com/UC-OSPO-Network/ucospo.net/blob/main/events/uc-open-4-2025/sessions/oss-security-ai.md","edit_url":"https://github.com/UC-OSPO-Network/ucospo.net/edit/main/events/uc-open-4-2025/sessions/oss-security-ai.md","exports":[{"format":"md","filename":"oss-security-ai.md","url":"/uc-ospo-network.github.io/build/oss-security-ai-528ead89fe37abd8a5b3791295afd817.md"}]},"mdast":{"type":"root","children":[{"type":"block","children":[{"type":"paragraph","position":{"start":{"line":5,"column":1},"end":{"line":6,"column":1}},"children":[{"type":"strong","position":{"start":{"line":5,"column":1},"end":{"line":5,"column":1}},"children":[{"type":"text","value":"Date:","position":{"start":{"line":5,"column":1},"end":{"line":5,"column":1}},"key":"xotFkunIeB"}],"key":"xKqAoxbdTk"},{"type":"text","value":" Thursday, April 24 2025","position":{"start":{"line":5,"column":1},"end":{"line":5,"column":1}},"key":"dQdNkRFOQx"},{"type":"break","position":{"start":{"line":5,"column":1},"end":{"line":5,"column":1}},"key":"qg1wO0LPvj"},{"type":"strong","position":{"start":{"line":5,"column":1},"end":{"line":5,"column":1}},"children":[{"type":"text","value":"Time:","position":{"start":{"line":5,"column":1},"end":{"line":5,"column":1}},"key":"mB0gs4xzu4"}],"key":"HjK7TBXkAh"},{"type":"text","value":" 10:30-11:20","position":{"start":{"line":5,"column":1},"end":{"line":5,"column":1}},"key":"xXRRlnSyK4"}],"key":"RVeGMgJHAN"},{"type":"paragraph","position":{"start":{"line":8,"column":1},"end":{"line":8,"column":1}},"children":[{"type":"strong","position":{"start":{"line":8,"column":1},"end":{"line":8,"column":1}},"children":[{"type":"text","value":"Moderators","position":{"start":{"line":8,"column":1},"end":{"line":8,"column":1}},"key":"JIa9g8iUtt"}],"key":"oO0OualyE3"},{"type":"text","value":":","position":{"start":{"line":8,"column":1},"end":{"line":8,"column":1}},"key":"gryN3GgnZX"}],"key":"Lm1gV9eKIO"},{"type":"list","ordered":false,"spread":false,"position":{"start":{"line":10,"column":1},"end":{"line":12,"column":1}},"children":[{"type":"listItem","spread":true,"position":{"start":{"line":10,"column":1},"end":{"line":10,"column":1}},"children":[{"type":"paragraph","children":[{"type":"link","url":"/events/uc-open-4-2025/speakers/alvaro-cardenas","position":{"start":{"line":10,"column":1},"end":{"line":10,"column":1}},"children":[{"type":"text","value":"Alvaro Cardenas UCSC","position":{"start":{"line":10,"column":1},"end":{"line":10,"column":1}},"key":"AZ3e7hkn6m"}],"urlSource":"../speakers/alvaro-cardenas.md","dataUrl":"/events.uc-open-4-2025.speakers.alvaro-cardenas.json","internal":true,"protocol":"file","key":"j9gWwFGJfD"}],"key":"axxbFvhYHC"}],"key":"FGtN1LDkRK"},{"type":"listItem","spread":true,"position":{"start":{"line":11,"column":1},"end":{"line":12,"column":1}},"children":[{"type":"paragraph","children":[{"type":"link","url":"/events/uc-open-4-2025/speakers/juanita-gomez","position":{"start":{"line":11,"column":1},"end":{"line":11,"column":1}},"children":[{"type":"text","value":"Juanita Gomez UCSC","position":{"start":{"line":11,"column":1},"end":{"line":11,"column":1}},"key":"aJ4MnnkLei"}],"urlSource":"../speakers/juanita-gomez.md","dataUrl":"/events.uc-open-4-2025.speakers.juanita-gomez.json","internal":true,"protocol":"file","key":"Mdqb2gS2J0"}],"key":"Qy3nqC1PrP"}],"key":"WbirunU2TG"}],"key":"B89spTtmuf"},{"type":"paragraph","position":{"start":{"line":13,"column":1},"end":{"line":13,"column":1}},"children":[{"type":"strong","position":{"start":{"line":13,"column":1},"end":{"line":13,"column":1}},"children":[{"type":"text","value":"Panelist:","position":{"start":{"line":13,"column":1},"end":{"line":13,"column":1}},"key":"Pv4xD2fvCm"}],"key":"qHVrgZflVs"}],"key":"XCvvBrKXhp"},{"type":"list","ordered":false,"spread":false,"position":{"start":{"line":15,"column":1},"end":{"line":16,"column":1}},"children":[{"type":"listItem","spread":true,"position":{"start":{"line":15,"column":1},"end":{"line":16,"column":1}},"children":[{"type":"paragraph","children":[{"type":"link","url":"/events/uc-open-4-2025/speakers/mihai-maruseac","position":{"start":{"line":15,"column":1},"end":{"line":15,"column":1}},"children":[{"type":"text","value":"Mihai Maruseac (Google)","position":{"start":{"line":15,"column":1},"end":{"line":15,"column":1}},"key":"eozVtlWqmt"}],"urlSource":"../speakers/mihai-maruseac.md","dataUrl":"/events.uc-open-4-2025.speakers.mihai-maruseac.json","internal":true,"protocol":"file","key":"STFeUlluKb"}],"key":"exOr55S32A"}],"key":"dBsFy1xyHS"}],"key":"YiT2zJkj6Q"},{"type":"heading","depth":2,"position":{"start":{"line":17,"column":1},"end":{"line":17,"column":1}},"children":[{"type":"text","value":"Description","position":{"start":{"line":17,"column":1},"end":{"line":17,"column":1}},"key":"MA8gb37hLD"}],"identifier":"description","label":"Description","html_id":"description","implicit":true,"key":"r7JnvX5gCJ"},{"type":"paragraph","position":{"start":{"line":19,"column":1},"end":{"line":19,"column":1}},"children":[{"type":"text","value":"In this session, Mihai will introduce the first stable release of an open-source model signing library developed in collaboration with NVIDIA and HiddenLayer.","position":{"start":{"line":19,"column":1},"end":{"line":19,"column":1}},"key":"SWgVaN6c1i"}],"key":"g7vRgrmXlB"},{"type":"paragraph","position":{"start":{"line":21,"column":1},"end":{"line":21,"column":1}},"children":[{"type":"text","value":"It is essential to ensure Machine Learning models integrity and provenance as they become more integrated into critical applications. This session will highlight the security challenges of the ML supply chain and demonstrate how cryptographic signatures, leveraging tools like Sigstore, can help users verify that the models they use are exactly those produced by trusted developers.","position":{"start":{"line":21,"column":1},"end":{"line":21,"column":1}},"key":"CIaEJkSANa"}],"key":"aVXQItGXP2"}],"key":"ISuA2Jq5hl"}],"key":"bO9DpnW1ef"},"references":{"cite":{"order":[],"data":{}}},"footer":{},"domain":"http://localhost:3000"}