{"version":3,"kind":"Article","sha256":"4c3ea286fd580060421c507ad61db3751acd9f5b0d713eda978566a4944c6582","slug":"events.uc-open-4-2025.sessions.agrifood","location":"/events/uc-open-4-2025/sessions/agrifood.md","dependencies":[],"frontmatter":{"title":"Open Source for Agrifood – Perspectives from Academia and Industry","github":"https://github.com/UC-OSPO-Network/ucospo.net","copyright":"2024","numbering":{"title":{"offset":1}},"source_url":"https://github.com/UC-OSPO-Network/ucospo.net/blob/main/events/uc-open-4-2025/sessions/agrifood.md","edit_url":"https://github.com/UC-OSPO-Network/ucospo.net/edit/main/events/uc-open-4-2025/sessions/agrifood.md","exports":[{"format":"md","filename":"agrifood.md","url":"/build/agrifood-993d3902db18601f9d96ba59ea7542a7.md"}]},"mdast":{"type":"root","children":[{"type":"block","children":[{"type":"paragraph","position":{"start":{"line":5,"column":1},"end":{"line":6,"column":1}},"children":[{"type":"strong","position":{"start":{"line":5,"column":1},"end":{"line":5,"column":1}},"children":[{"type":"text","value":"Date:","position":{"start":{"line":5,"column":1},"end":{"line":5,"column":1}},"key":"RTq78Nwa02"}],"key":"oi5KgALHlY"},{"type":"text","value":" Thursday, April 24 2025","position":{"start":{"line":5,"column":1},"end":{"line":5,"column":1}},"key":"kQLCS8Z2eY"},{"type":"break","position":{"start":{"line":5,"column":1},"end":{"line":5,"column":1}},"key":"vgpQHupD8J"},{"type":"strong","position":{"start":{"line":5,"column":1},"end":{"line":5,"column":1}},"children":[{"type":"text","value":"Time:","position":{"start":{"line":5,"column":1},"end":{"line":5,"column":1}},"key":"M5ewIGln22"}],"key":"sGGhjjxDeE"},{"type":"text","value":" 11:25-12:35","position":{"start":{"line":5,"column":1},"end":{"line":5,"column":1}},"key":"Y9AXzEvWn2"}],"key":"UX0IHJWBIS"},{"type":"paragraph","position":{"start":{"line":8,"column":1},"end":{"line":8,"column":1}},"children":[{"type":"strong","position":{"start":{"line":8,"column":1},"end":{"line":8,"column":1}},"children":[{"type":"text","value":"Moderator","position":{"start":{"line":8,"column":1},"end":{"line":8,"column":1}},"key":"gX5tonyic1"}],"key":"WxV6RLEp5u"},{"type":"text","value":": ","position":{"start":{"line":8,"column":1},"end":{"line":8,"column":1}},"key":"WmMXQ6jGRG"},{"type":"link","url":"/events/uc-open-4-2025/speakers/rob-trice","position":{"start":{"line":8,"column":1},"end":{"line":8,"column":1}},"children":[{"type":"text","value":"Rob Trice (Partner, Better Food Ventures)","position":{"start":{"line":8,"column":1},"end":{"line":8,"column":1}},"key":"RUgkDZnZVW"}],"urlSource":"../speakers/rob-trice.md","dataUrl":"/events.uc-open-4-2025.speakers.rob-trice.json","internal":true,"protocol":"file","key":"jgf4EjGlHJ"}],"key":"kxTx3gIauW"},{"type":"paragraph","position":{"start":{"line":10,"column":1},"end":{"line":10,"column":1}},"children":[{"type":"strong","position":{"start":{"line":10,"column":1},"end":{"line":10,"column":1}},"children":[{"type":"text","value":"Panelists","position":{"start":{"line":10,"column":1},"end":{"line":10,"column":1}},"key":"CIuEmuubtn"}],"key":"SEDuyg2qGt"},{"type":"text","value":":","position":{"start":{"line":10,"column":1},"end":{"line":10,"column":1}},"key":"iE6FcyBS7o"}],"key":"lKFL4XXzWs"},{"type":"list","ordered":false,"spread":false,"position":{"start":{"line":12,"column":1},"end":{"line":16,"column":1}},"children":[{"type":"listItem","spread":true,"position":{"start":{"line":12,"column":1},"end":{"line":12,"column":1}},"children":[{"type":"paragraph","children":[{"type":"link","url":"/events/uc-open-4-2025/speakers/priscilla-koepke","position":{"start":{"line":12,"column":1},"end":{"line":12,"column":1}},"children":[{"type":"text","value":"Priscilla Koepke (CEO, F3 Innovate)","position":{"start":{"line":12,"column":1},"end":{"line":12,"column":1}},"key":"BlwyWEkDxH"}],"urlSource":"../speakers/priscilla-koepke.md","dataUrl":"/events.uc-open-4-2025.speakers.priscilla-koepke.json","internal":true,"protocol":"file","key":"M1mu8BOpD7"}],"key":"FFJNE385wi"}],"key":"elimeWp6YE"},{"type":"listItem","spread":true,"position":{"start":{"line":13,"column":1},"end":{"line":13,"column":1}},"children":[{"type":"paragraph","children":[{"type":"link","url":"/events/uc-open-4-2025/speakers/colleen-josephson","position":{"start":{"line":13,"column":1},"end":{"line":13,"column":1}},"children":[{"type":"text","value":"Colleen Josephson (Assistant Professor, Dept. of Electrical and Computer Engineering, Co-Director, Agtech Alliance, UCSC)","position":{"start":{"line":13,"column":1},"end":{"line":13,"column":1}},"key":"IqOT7W2Gcf"}],"urlSource":"../speakers/colleen-josephson.md","dataUrl":"/events.uc-open-4-2025.speakers.colleen-josephson.json","internal":true,"protocol":"file","key":"cNvlJay0Bw"}],"key":"hO2ovRRigW"}],"key":"zbkwSuOTi8"},{"type":"listItem","spread":true,"position":{"start":{"line":14,"column":1},"end":{"line":14,"column":1}},"children":[{"type":"paragraph","children":[{"type":"link","url":"/events/uc-open-4-2025/speakers/gabe-youtsey","position":{"start":{"line":14,"column":1},"end":{"line":14,"column":1}},"children":[{"type":"text","value":"Gabe Youtsey (CIO, UC Agriculture & Natural Resources)","position":{"start":{"line":14,"column":1},"end":{"line":14,"column":1}},"key":"CDgg0JetwD"}],"urlSource":"../speakers/gabe-youtsey.md","dataUrl":"/events.uc-open-4-2025.speakers.gabe-youtsey.json","internal":true,"protocol":"file","key":"NauE1PvaQb"}],"key":"Nmrvghbzj4"}],"key":"YIqa6ypdGI"},{"type":"listItem","spread":true,"position":{"start":{"line":15,"column":1},"end":{"line":16,"column":1}},"children":[{"type":"paragraph","children":[{"type":"link","url":"/events/uc-open-4-2025/speakers/drew-zabrocki","position":{"start":{"line":15,"column":1},"end":{"line":15,"column":1}},"children":[{"type":"text","value":"Drew Zabrocki (International Fresh Produce Association, Fresh Supply Chain of the Future)","position":{"start":{"line":15,"column":1},"end":{"line":15,"column":1}},"key":"C7gXGtgytt"}],"urlSource":"../speakers/drew-zabrocki.md","dataUrl":"/events.uc-open-4-2025.speakers.drew-zabrocki.json","internal":true,"protocol":"file","key":"ztTDCX24X6"}],"key":"vF19UM63J3"}],"key":"uC0rt21Qqy"}],"key":"CogexhKOdG"},{"type":"heading","depth":2,"position":{"start":{"line":17,"column":1},"end":{"line":17,"column":1}},"children":[{"type":"text","value":"Description","position":{"start":{"line":17,"column":1},"end":{"line":17,"column":1}},"key":"AXnEfG4SQv"}],"identifier":"description","label":"Description","html_id":"description","implicit":true,"key":"IWpNqmCGC2"},{"type":"paragraph","position":{"start":{"line":19,"column":1},"end":{"line":19,"column":1}},"children":[{"type":"text","value":"Over $200 billion of venture capital money has been invested in the agrifood sector over the last decade. There are over 150 dedicated tech incubators, accelerators and venture support organizations around the world dedicated to agriculture. Yet we have yet to solve major challenges related to food production and processing. We need new models of innovation and open innovation is a tool that has been under utilized in a sector with very little profit margin historically. How can we better leverage open software and systems and greater collaboration to meet agriculture’s numerous challenges?","position":{"start":{"line":19,"column":1},"end":{"line":19,"column":1}},"key":"WKF7D41OSL"}],"key":"mEcZi64sps"}],"key":"VDGP5qSi1u"}],"key":"YCaMvaCyLC"},"references":{"cite":{"order":[],"data":{}}},"footer":{},"domain":"http://localhost:3000"}